jtable/__init__.py
jtable/__main__.py
jtable/functions.py
jtable/jtable.py
jtable/jtable_filter.py
jtable/jtable_play.py
jtable/jtable_template.py
jtable/logger.py
jtable/player.py
jtable/templater.py
jtable/version.py
jtable/Styling/__init__.py
jtable/Styling/color_table.py
jtable/resources/__init__.py
jtable/resources/js_wrapper.css
jtable/resources/js_wrapper.js
jtable/to_table/__init__.py
jtable/to_table/jinja_path_splitter.py
jtable-0.11.56.dist-info/licenses/LICENSE.txt
jtable-0.11.56.dist-info/METADATA
jtable-0.11.56.dist-info/WHEEL
jtable-0.11.56.dist-info/entry_points.txt
jtable-0.11.56.dist-info/top_level.txt
jtable-0.11.56.dist-info/RECORD
